ddsl_lambda_wg/__init__.py
ddsl_lambda_wg/timer.py
ddsl_lambda_wg/wg.py
ddsl_lambda_wg-0.1.5.dist-info/LICENSE
ddsl_lambda_wg-0.1.5.dist-info/METADATA
ddsl_lambda_wg-0.1.5.dist-info/WHEEL
ddsl_lambda_wg-0.1.5.dist-info/top_level.txt
ddsl_lambda_wg-0.1.5.dist-info/RECORD
