Metadata-Version: 2.1
Name: ddsl-lambda-wg
Version: 0.1.5
Summary: This is a workload generator for aws lambda.
Home-page: https://github.com/nimamahmoudi/ddsl_lambda_workload_generator
Author: Nima Mahmoudi
Author-email: nima_mahmoudi@live.com
License: UNKNOWN
Platform: UNKNOWN
Classifier: Development Status :: 3 - Alpha
Classifier: Programming Language :: Python
Classifier: Programming Language :: Python :: 3
Classifier: Programming Language :: Python :: 3.6
Classifier: Intended Audience :: Developers
Classifier: License :: OSI Approved :: MIT License
Classifier: Operating System :: OS Independent
Requires-Dist: numpy (>=1.16.4)
Requires-Dist: boto3 (>=1.9.170)
Requires-Dist: pandas (>=0.24.2)
